nexstarpy/__init__.py
nexstarpy/constants.py
nexstarpy/exceptions.py
nexstarpy/nexstar.py
nexstarpy-0.1.0.dist-info/METADATA
nexstarpy-0.1.0.dist-info/WHEEL
nexstarpy-0.1.0.dist-info/RECORD
