Metadata-Version: 2.3
Name: nexstarpy
Version: 0.1.0
Summary: 
Author: Iván Salazar
Author-email: ivangio.salazar@gmail.com
Requires-Python: >=3.13
Classifier: Programming Language :: Python :: 3
Classifier: Programming Language :: Python :: 3.13
Requires-Dist: pyserial (>=3.5,<4.0)
